__init__.py
main.py
store/__init__.py
store/store.py
store/customer/__init__.py
store/customer/customer.py
store/customer/person.py
store/pos/__init__.py
store/pos/pos.py
store/product/__init__.py
store/product/product.py
shop_python-0.0.1.dist-info/METADATA
shop_python-0.0.1.dist-info/WHEEL
shop_python-0.0.1.dist-info/licenses/LICENSE
shop_python-0.0.1.dist-info/RECORD
